httpie_curl_cffi/__init__.py
httpie_curl_cffi-1.0.0a1.dist-info/METADATA
httpie_curl_cffi-1.0.0a1.dist-info/WHEEL
httpie_curl_cffi-1.0.0a1.dist-info/entry_points.txt
httpie_curl_cffi-1.0.0a1.dist-info/licenses/LICENSE
httpie_curl_cffi-1.0.0a1.dist-info/RECORD
