Metadata-Version: 2.3
Name: httpie-curl-cffi
Version: 1.0.0a1
Summary: HTTPie plugin for using curl_cffi as transport
Author-email: Xie Yanbo <xieyanbo@gmail.com>
License: MIT
Classifier: Development Status :: 4 - Beta
Classifier: Environment :: Plugins
Classifier: Programming Language :: Python :: 3
Classifier: Programming Language :: Python :: 3.7
Classifier: Programming Language :: Python :: 3.8
Classifier: Programming Language :: Python :: 3.9
Classifier: Programming Language :: Python :: 3.10
Classifier: Programming Language :: Python :: 3.11
Classifier: Topic :: Internet :: WWW/HTTP
Classifier: Topic :: Software Development :: Libraries :: Python Modules
Requires-Python: >=3.7
Requires-Dist: curl-cffi>=0.5.0
Requires-Dist: httpie>=3.0.0
